{
  "__catalogCourseId": "ANTH302",
  "__passedCatalogQuery": true,
  "_score": 1,
  "catalogActivationDate": "2019-11-15",
  "credits": {
    "chosen": "fixed",
    "credits": {
      "max": "1.5",
      "min": "1.5"
    },
    "value": "1.5"
  },
  "dateStart": "2020-01-01",
  "description": "<p>A comparative framework for understanding the relationship between global processes, the environment and health. Topics may include the origin and evolution of infectious diseases with human societies, social and economic inequalities, violence, gender, diet, health policies, technologies, pandemics, climate change, and health care industries. Emphasis on how local experiences of health are linked to global processes via the environment.</p>",
  "groupFilter1": {
    "customFields": {},
    "id": "5be3636156a15d000126de7e",
    "name": "Department of Anthropology"
  },
  "hoursCatalogText": "3-0-0",
  "id": "5d1f6ff4d2bc1524008cb17a",
  "pid": "ByZwpwam4",
  "preAndCorequisites": "<div><div><div><ul><li data-test=\"ruleView-A\"><div data-test=\"ruleView-A-result\"><div>Minimum second-year standing.</div></div></li></ul></div></div></div>",
  "proForma": "no",
  "subjectCode": {
    "description": "Anthropology (ANTH)",
    "id": "5be1fb162ce2be2e00301722",
    "linkedGroup": "5be3636156a15d000126de7e",
    "name": "ANTH"
  },
  "supplementalNotes": "",
  "title": "Globalization, Health, and the Environment"
}
