{
  "__catalogCourseId": "EOS202",
  "__passedCatalogQuery": true,
  "_score": 1,
  "catalogActivationDate": "2019-11-15",
  "credits": {
    "chosen": "fixed",
    "credits": {
      "max": "1.5",
      "min": "1.5"
    },
    "value": "1.5"
  },
  "dateStart": "2020-01-01",
  "description": "<p>Geometric, kinematic and dynamic analysis of deformation structures in rock bodies at different scales, in both brittle and ductile regimes. Stress and strain in rocks and their relationship to geologic structures. Interpretation of the physical mechanisms of folding and faulting in rocks with structural data and geological maps. The origin of crustal deformation in the context of plate tectonics.</p>",
  "groupFilter1": {
    "customFields": {},
    "id": "5be3691afed2d200010da13f",
    "name": "School of Earth and Ocean Sciences"
  },
  "hoursCatalogText": "3-3-0",
  "id": "5d1f6a1494e82e2400a23140",
  "pid": "H1V3XuTX4",
  "preAndCorequisites": "<div><div><div><ul><li data-test=\"ruleView-A\"><div data-test=\"ruleView-A-result\">Complete all of: <div><ul style=\"margin-top:5px;margin-bottom:5px\"><li><span><a href=\"#/courses/view/5d1f6b5889944f24002ad041\" target=\"_blank\">EOS120</a> <!-- -->-<!-- --> <!-- -->The Dynamic Earth<!-- --> <span style=\"margin-left:5px\">(1.5)</span></span></li></ul></div></div></li></ul></div></div></div>",
  "proForma": "no",
  "subjectCode": {
    "description": "Earth and Ocean Sciences (EOS)",
    "id": "5c13fb3b42504f2400e645d8",
    "linkedGroup": "5be3691afed2d200010da13f",
    "name": "EOS"
  },
  "supplementalNotes": "",
  "title": "Structural Geology"
}
